CASTLE/ABA_annotation.py
CASTLE/__init__.py
CASTLE/emb_alignment.py
CASTLE/loc_alignment.py
CASTLE/loc_prediction.py
CASTLE/utils.py
CASTLE_tools-1.1.dist-info/LICENSE.txt
CASTLE_tools-1.1.dist-info/METADATA
CASTLE_tools-1.1.dist-info/WHEEL
CASTLE_tools-1.1.dist-info/top_level.txt
CASTLE_tools-1.1.dist-info/RECORD
