Metadata-Version: 2.1
Name: CASTLE-tools
Version: 1.1
Summary: Complete Alignment of spatial transcriptomics in Location and Embedding
Home-page: UNKNOWN
Author: yuanyuanyu
Author-email: UNKNOWN
License: MIT
Platform: UNKNOWN
